{"id": 1, "data": {"text": "O Campo de Miranga,     Arenitos Catu    Forma\u00e7\u00e3o Pojuca, incorpo-rou um volume de mais de 600 milh\u00f5es de barris de \u00f3leo in-place.."}, "annotations": [{"id": 1, "created_username": " null, 0", "created_ago": "", "result": [{"value": {"start": "41", "end": "56", "text": " Forma\u00e7\u00e3o Pojuca", "labels": ["UNIDADE_LITO"], "URI": "#formacao_287"}, "id": 7.0, "from_name": "label", "to_name": "text", "type": "labels", "origin": "prediction"}, {"value": {"start": "24", "end": "37", "text": " Arenitos Catu", "labels": ["ROCHA"], "URI": "#sandstone"}, "id": 5.0, "from_name": "label", "to_name": "text", "type": "labels", "origin": "prediction"}, {"from_id": "2", "to_id": "1", "type": "relation", "direction": "right", "labels": ["constituted_by"]}]}]}