{"id": 1, "data": {"text": "O Membro Mucuri              de sedimentos de idades Alagoas e pr\u00e9-Alagoas depositados em ambiente al\u00favio-fl\u00favio-deltaico, sob clima \u00e1rido, durante a fase rift     bacias    Espirito Santo e Mucuri.."}, "annotations": [{"id": 1, "created_username": " null, 0", "created_ago": "", "result": [{"value": {"start": "2", "end": "15", "text": " Membro Mucuri", "labels": ["UNIDADE_LITO"], "URI": "#membro_010"}, "id": 1.0, "from_name": "label", "to_name": "text", "type": "labels", "origin": "prediction"}, {"value": {"start": "46", "end": "60", "text": " idades Alagoas", "labels": ["UNIDADE_CRONO"], "URI": "#Alagoas_Age"}, "id": 6.0, "from_name": "label", "to_name": "text", "type": "labels", "origin": "prediction"}, {"value": {"start": "63", "end": "74", "text": " pr\u00e9-Alagoas", "labels": ["UNIDADE_CRONO"], "URI": "#Alagoas_Age"}, "id": 9.0, "from_name": "label", "to_name": "text", "type": "labels", "origin": "prediction"}, {"from_id": "0", "to_id": "2", "type": "relation", "direction": "right", "labels": ["has_age"]}, {"from_id": "0", "to_id": "3", "type": "relation", "direction": "right", "labels": ["has_age"]}, {"from_id": "2", "to_id": "3", "type": "relation", "direction": "right", "labels": ["temporal_relation"]}, {"from_id": "3", "to_id": "2", "type": "relation", "direction": "right", "labels": ["temporal_relation"]}]}]}