{"id": 1, "data": {"text": "O colapso gravitacional continuou vigoro-samente      Neo-eoceno/Oligoceno/Eomioceno (idades    maioria     dep\u00f3sitos sedimentares    SRCSB).."}, "annotations": [{"id": 1, "created_username": " null, 0", "created_ago": "", "result": [{"value": {"start": "54", "end": "65", "text": " Neo-eoceno/", "labels": ["UNIDADE_CRONO"], "URI": "#Priabonian"}, "id": 5.0, "from_name": "label", "to_name": "text", "type": "labels", "origin": "prediction"}, {"value": {"start": "65", "end": "75", "text": " Oligoceno/", "labels": ["UNIDADE_CRONO"], "URI": "#Oligocene"}, "id": 6.0, "from_name": "label", "to_name": "text", "type": "labels", "origin": "prediction"}, {"from_id": "0", "to_id": "1", "type": "relation", "direction": "right", "labels": ["temporal_relation"]}, {"from_id": "1", "to_id": "0", "type": "relation", "direction": "right", "labels": ["temporal_relation"]}]}]}